linecount/__init__.py
linecount/cli.py
linecount/exceptions.py
linecount/line_counting.py
linecount-1.1.3.dist-info/LICENSE
linecount-1.1.3.dist-info/METADATA
linecount-1.1.3.dist-info/WHEEL
linecount-1.1.3.dist-info/entry_points.txt
linecount-1.1.3.dist-info/top_level.txt
linecount-1.1.3.dist-info/RECORD
