Metadata-Version: 2.1
Name: linecount
Version: 1.1.3
Summary: Count lines of files!
Author: AlexanderJCS
Project-URL: repository, https://github.com/AlexanderJCS/line-count
Project-URL: homepage, https://github.com/AlexanderJCS/line-count
Project-URL: issues, https://github.com/AlexanderJCS/line-count/issues
Classifier: Programming Language :: Python :: 3
Classifier: License :: OSI Approved :: MIT License
Classifier: Operating System :: OS Independent
Requires-Python: >=3.6
License-File: LICENSE
